rhasspy_skills_cli/__init__.py
rhasspy_skills_cli/__main__.py
rhasspy_skills_cli/main.py
rhasspy_skills_cli/manifest.py
rhasspy_skills_cli-0.3.0.dist-info/entry_points.txt
rhasspy_skills_cli-0.3.0.dist-info/LICENSE
rhasspy_skills_cli-0.3.0.dist-info/WHEEL
rhasspy_skills_cli-0.3.0.dist-info/METADATA
rhasspy_skills_cli-0.3.0.dist-info/RECORD
