Metadata-Version: 2.1
Name: rhasspy-skills-cli
Version: 0.3.0
Summary: 
License: MIT
Author: razzo04
Author-email: razzorazzo1@gmail.com
Requires-Python: >=3.7,<4.0
Classifier: License :: OSI Approved :: MIT License
Classifier: Programming Language :: Python :: 3
Classifier: Programming Language :: Python :: 3.7
Classifier: Programming Language :: Python :: 3.8
Classifier: Programming Language :: Python :: 3.9
Requires-Dist: GitPython (==3.1.18)
Requires-Dist: httpx (==0.18.2)
Requires-Dist: pydantic (==1.8.2)
Requires-Dist: typer (==0.3.2)
